effconnpy/__init__.py
effconnpy/analyzers.py
effconnpy/extendedanalyzers.py
effconnpy/multivariateCCM.py
effconnpy/multivariateGC.py
effconnpy/multivariateTE.py
effconnpy/nonlinearGC.py
effconnpy/timeseriesgenerator.py
effconnpy/utils.py
effconnpy/vis_brainstorm.py
effconnpy/vis_dyn.py
effconnpy/vis_effconn.py
effconnpy/vis_effconn_tracts.py
effconnpy-0.1.25.dist-info/METADATA
effconnpy-0.1.25.dist-info/WHEEL
effconnpy-0.1.25.dist-info/top_level.txt
effconnpy-0.1.25.dist-info/RECORD
