Metadata-Version: 2.4
Name: effconnpy
Version: 0.1.25
Summary: A package for causal inference and statistical modeling in brain time series
Home-page: https://github.com/alecrimi/effconnpy
Author: Alessandro Crimi
Author-email: alecrimi@agh.edu.pl
License: MIT
Classifier: Programming Language :: Python :: 3
Classifier: License :: OSI Approved :: MIT License
Classifier: Operating System :: OS Independent
Classifier: Intended Audience :: Science/Research
Classifier: Topic :: Scientific/Engineering :: Mathematics
Classifier: Topic :: Scientific/Engineering :: Artificial Intelligence
Requires-Python: >=3.7
Requires-Dist: numpy
Requires-Dist: pandas
Requires-Dist: statsmodels
Requires-Dist: scipy
Requires-Dist: copent
Requires-Dist: networkx
Requires-Dist: dowhy
Requires-Dist: pymc3
Requires-Dist: arviz
Dynamic: author
Dynamic: author-email
Dynamic: classifier
Dynamic: description
Dynamic: description-content-type
Dynamic: home-page
Dynamic: license
Dynamic: requires-dist
Dynamic: requires-python
Dynamic: summary
